feature_test/__init__.py
feature_test/feature_tests.py
feature_test/input_errors.py
feature_test/tests.py
feature_test/utils.py
feature_test-0.1.21.dist-info/LICENSE
feature_test-0.1.21.dist-info/METADATA
feature_test-0.1.21.dist-info/WHEEL
feature_test-0.1.21.dist-info/top_level.txt
feature_test-0.1.21.dist-info/RECORD
