Metadata-Version: 2.1
Name: feature-test
Version: 0.1.21
Summary: examines the relationships between a new feature and everyother feature in a dataset
Home-page: https://gitlab.cee.redhat.com/twileman/feature_test
Author: Thomas Wilmean
Author-email: twileman@redhat.com
License: MIT License
Project-URL: Bug Tracker, https://gitlab.cee.redhat.com/twileman/feature_test
Classifier: License :: OSI Approved :: MIT License
Classifier: Programming Language :: Python :: 3
Classifier: Operating System :: OS Independent
Requires-Python: >=3.6
License-File: LICENSE
Requires-Dist: numpy (>=1.21.5)
Requires-Dist: pandas (>=1.1.2)
Requires-Dist: scipy (>=1.5.2)
Requires-Dist: scikit-learn
